[
  {
    "text": "[Section 7] xc2 xb7 xc2 xb7 xc2 xb7 xc2 xb7 xc2 xb7 xc2 xb7 xc2 xb7 xc2 xb7 xc2 xb7 xc2 xb7 xc2 xb7 xc2 xb7 xc2 xb7 xc2 xb7 xc2 xb7 xc2 xb7 xc2 xb7 xc2 xb7 xc2 xb715 6 theoretical framework xc2 xb7 xc2 xb7 xc2 xb7 xc2 xb7 xc2 xb7 xc2 xb7 xc2 xb7 xc2 xb7 xc2 xb7 xc2 xb7 xc2 xb7 xc2 xb7 xc2 xb7 xc2 xb7 xc2 xb7 xc2 xb7 xc2 xb7 xc2 xb7 xc2 xb7 xc2 xb7 xc2 xb7 xc2 xb7 xc2 xb7 xc2 xb7 xc2 xb7 xc2 xb7 xc2 xb7 xc2 xb7 xc2 xb7 xc2 xb7 xc2 xb7 xc2 xb7 xc2 xb7 xc2 xb7 xc2 xb7 xc2 xb7 xc2 xb7 xc2 xb7 xc2 xb7 xc2 xb7 xc2 xb7 xc2 xb7 xc2 xb7 xc2 xb7 xc2 xb7 xc2 xb7 xc2 xb7 xc2 xb7 xc2 xb7 xc2 xb7 xc2 xb7 xc2 xb7 xc2 xb7 xc2 xb7 xc2 xb7 xc2 xb7 xc2 xb7 xc2 xb7 xc2 xb7 xc2 xb7 xc2 xb7 xc2 xb7 xc2 xb7 xc2 xb7 xc2 xb7 xc2 xb7 xc2 xb7 xc2 xb7 xc2 xb7 xc2 xb7 xc2 xb7 xc2 xb7 xc2 xb7 xc2 xb7 xc2 xb7 xc2 xb7 xc2 xb7 xc2 xb7 xc2 xb7 xc2 xb7 xc2 xb7 xc2 xb716 6 1 laws data value embedded parameters xc2 xb7 xc2 xb7 xc2 xb7 xc2 xb7 xc2 xb7 xc2 xb7 xc2 xb7 xc2 xb7 xc2 xb7 xc2 xb7 xc2 xb7 xc2 xb7 xc2 xb7 xc2 xb7 xc2 xb7 xc2",
    "metadata": {
      "chunk_id": "9454600b35a910e58927826a7e4fddb3",
      "entities": {
        "email": [],
        "crypto_address": []
      },
      "risk_features": {
        "regulatory": [],
        "technical": [],
        "financial": [],
        "operational": []
      },
      "risk_score": 0.0,
      "source": "Banyan Network.txt"
    }
  },
  {
    "text": "[Section 8] xc2 xb7 xc2 xb7 xc2 xb7 xc2 xb716 6 1 laws data value embedded parameters xc2 xb7 xc2 xb7 xc2 xb7 xc2 xb7 xc2 xb7 xc2 xb7 xc2 xb7 xc2 xb7 xc2 xb7 xc2 xb7 xc2 xb7 xc2 xb7 xc2 xb7 xc2 xb7 xc2 xb7 xc2 xb7 xc2 xb7 xc2 xb7 xc2 xb7 xc2 xb7 xc2 xb7 xc2 xb7 xc2 xb7 xc2 xb7 xc2 xb7 xc2 xb7 xc2 xb7 xc2 xb7 xc2 xb7 xc2 xb7 xc2 xb7 xc2 xb7 xc2 xb7 xc2 xb7 xc2 xb7 xc2 xb7 xc2 xb7 xc2 xb7 xc2 xb7 xc2 xb7 xc2 xb7 xc2 xb716 6 2 parameter data quality xc2 xb7 xc2 xb7 xc2 xb7 xc2 xb7 xc2 xb7 xc2 xb7 xc2 xb7 xc2 xb7 xc2 xb7 xc2 xb7 xc2 xb7 xc2 xb7 xc2 xb7 xc2 xb7 xc2 xb7 xc2 xb7 xc2 xb7 xc2 xb7 xc2 xb7 xc2 xb7 xc2 xb7 xc2 xb7 xc2 xb7 xc2 xb7 xc2 xb7 xc2 xb7 xc2 xb7 xc2 xb7 xc2 xb7 xc2 xb7 xc2 xb7 xc2 xb7 xc2 xb7 xc2 xb7 xc2 xb7 xc2 xb7 xc2 xb7 xc2 xb7 xc2 xb7 xc2 xb7 xc2 xb7 xc2 xb7 xc2 xb7 xc2 xb7 xc2 xb7 xc2 xb7 xc2 xb7 xc2 xb7 xc2 xb7 xc2 xb7 xc2 xb7 xc2 xb7 xc2 xb7 xc2 xb7 xc2 xb7 xc2 xb7 xc2 xb7 xc2 xb7 xc2 xb7 xc2 xb7 xc2 xb7 xc2 xb7 xc2 xb7 xc2 xb7 xc2 xb7 xc2 xb7 xc2 xb7 xc2 xb7 xc2 xb7 xc2 xb7",
    "metadata": {
      "chunk_id": "3b22de61063269dec9575a860a4679da",
      "entities": {
        "email": [],
        "crypto_address": []
      },
      "risk_features": {
        "regulatory": [],
        "technical": [],
        "financial": [],
        "operational": []
      },
      "risk_score": 0.0,
      "source": "Banyan Network.txt"
    }
  },
  {
    "text": "[Section 13] xc2 xb7 xc2 xb7 xc2 xb7 xc2 xb7 xc2 xb7 xc2 xb7 xc2 xb7 xc2 xb7 xc2 xb7 xc2 xb7 xc2 xb7 xc2 xb7 xc2 xb7 xc2 xb718 6 7 decision mechanisms definition data parameter functions xc2 xb7 xc2 xb7 xc2 xb7 xc2 xb7 xc2 xb7 xc2 xb7 xc2 xb7 xc2 xb7 xc2 xb7 xc2 xb7 xc2 xb7 xc2 xb7 xc2 xb7 xc2 xb7 xc2 xb7 xc2 xb7 xc2 xb7 xc2 xb7 xc2 xb7 xc2 xb7 xc2 xb7 xc2 xb718 7 rules tokens xc2 xb7 xc2 xb7 xc2 xb7 xc2 xb7 xc2 xb7 xc2 xb7 xc2 xb7 xc2 xb7 xc2 xb7 xc2 xb7 xc2 xb7 xc2 xb7 xc2 xb7 xc2 xb7 xc2 xb7 xc2 xb7 xc2 xb7 xc2 xb7 xc2 xb7 xc2 xb7 xc2 xb7 xc2 xb7 xc2 xb7 xc2 xb7 xc2 xb7 xc2 xb7 xc2 xb7 xc2 xb7 xc2 xb7 xc2 xb7 xc2 xb7 xc2 xb7 xc2 xb7 xc2 xb7 xc2 xb7 xc2 xb7 xc2 xb7 xc2 xb7 xc2 xb7 xc2 xb7 xc2 xb7 xc2 xb7 xc2 xb7 xc2 xb7 xc2 xb7 xc2 xb7 xc2 xb7 xc2 xb7 xc2 xb7 xc2 xb7 xc2 xb7 xc2 xb7 xc2 xb7 xc2 xb7 xc2 xb7 xc2 xb7 xc2 xb7 xc2 xb7 xc2 xb7 xc2 xb7 xc2 xb7 xc2 xb7 xc2 xb7 xc2 xb7 xc2 xb7 xc2 xb7 xc2 xb7 xc2 xb7 xc2 xb7 xc2 xb7 xc2 xb7 xc2 xb7 xc2 xb7 xc2 xb7 xc2 xb7 xc2 xb7 xc2 xb7 xc2 xb7 xc2 xb7",
    "metadata": {
      "chunk_id": "c902faaa8bd08398206f13334919883d",
      "entities": {
        "email": [],
        "crypto_address": []
      },
      "risk_features": {
        "regulatory": [],
        "technical": [],
        "financial": [],
        "operational": []
      },
      "risk_score": 0.0,
      "source": "Banyan Network.txt"
    }
  },
  {
    "text": "[Section 28] technology world xe2 x80 x99s distributed ecosystem data economies raised built participants field data analytics value dvn based xe2 x80 x9csymbiosis mutual benefits common governance common prosperity xe2 x80 x9d goal focus blockchainenabled trusted data connection party data integration governance data applications open market development building positive interactive value linked network data benefits establishing standards providing channels issuing tokens data value network equipped extendable fast growing token system rich scenarios capable promoting data 3 x0cbanyan network aggregation widest range exciting data stream higher speeds enhancing usability integration values providing ways multiplying values data providers processors users generalized contributors field data analytics creating future sharing space unlimited value data value network adopts advanced data matching correction algorithms implement contribute reward computation mechanisms partnering resourceful",
    "metadata": {
      "chunk_id": "2e26545adc36957dedaff4508289fa5c",
      "entities": {
        "email": [],
        "crypto_address": []
      },
      "risk_features": {
        "regulatory": [],
        "technical": [],
        "financial": [],
        "operational": []
      },
      "risk_score": 0.0,
      "source": "Banyan Network.txt"
    }
  },
  {
    "text": "[Section 29] creating future sharing space unlimited value data value network adopts advanced data matching correction algorithms implement contribute reward computation mechanisms partnering resourceful mainstream commercial data providers basing initial values resources branding major clients providing convenient channels enterprise individual data sources joining xe2 x80 x9cdata value network ecosystem xe2 x80 x9d based theories xe2 x80 x9cthree laws data value xe2 x80 x9d mechanisms xe2 x80 x9ctripartite model xe2 x80 x9d data value network covers data collection cleansing integration applications complete business chains aggressively adopt latest technical solutions high performance blockchain hpb decentralized token exchange protocol loopring box computing bc ensure operation gradual expansion entire network 4 x0cbanyan network 2 abbreviation bbn1 xef xbc x88big banyan network xef xbc x89 dvc xef xbc x88data fusion value chain xef xbc x89 dvn xef xbc x88data fusion value chain network xef",
    "metadata": {
      "chunk_id": "99ad05eab2c9ae5e09c979a18bf27896",
      "entities": {
        "email": [],
        "crypto_address": []
      },
      "risk_features": {
        "regulatory": [],
        "technical": [],
        "financial": [],
        "operational": []
      },
      "risk_score": 0.0,
      "source": "Banyan Network.txt"
    }
  },
  {
    "text": "[Section 30] entire network 4 x0cbanyan network 2 abbreviation bbn1 xef xbc x88big banyan network xef xbc x89 dvc xef xbc x88data fusion value chain xef xbc x89 dvn xef xbc x88data fusion value chain network xef xbc x89 dpos xef xbc x88delegated proof stake xef xbc x89 irc xef xbc x88introducing rewards contract xef xbc x89 crc xef xbc x88cleaning rewards contract xef xbc x89 apc xef xbc x88apply pay contract xef xbc x89 tc xef xbc x88transaction contrac xef xbc x89 api xef xbc x88application programming interface xef xbc x89 hpb xef xbc x88high performance blockchain xef xbc x89 3 project background widespread big data applications era blockchain approaching common keyword big data blockchain xe2 x80 x9cdistributed xe2 x80 x9d representing future fundamental change technological authoritarianism monopoly decentralization data industry super industrial cluster huge market potential terms scale data infrastructure services automated transactions tens billions precision marketing pan regional",
    "metadata": {
      "chunk_id": "b5212151ec2c7ed4becc01d055fd328b",
      "entities": {
        "email": [],
        "crypto_address": []
      },
      "risk_features": {
        "regulatory": [],
        "technical": [],
        "financial": [],
        "operational": []
      },
      "risk_score": 0.0,
      "source": "Banyan Network.txt"
    }
  },
  {
    "text": "[Section 31] monopoly decentralization data industry super industrial cluster huge market potential terms scale data infrastructure services automated transactions tens billions precision marketing pan regional marketing 1 bbn token issued project 5 x0cbanyan network information verification business government personal market consulting hundreds billions market size practical industry applications reaches level trillion programmatic marketing classic product data applications example market size china 11 5 billion yuan 2016 reach 25 billion 2017 maintaining 20% compound annual growth rate 2020 digital marketing classic industry data applications market size china 240 billion yuan 2016 reach 280 billion yuan 2017 maintaining 15% compound annual growth rate 2020 overall industry total revenue china s big data related products services 340 billion yuan expected break 1 trillion yuan mark 2020 data industry facing intuitive obvious development bottleneck terms data sources barriers entry obtaining",
    "metadata": {
      "chunk_id": "7a4657885df0e267a70eb4a3f83d099f",
      "entities": {
        "location": [
          "china"
        ],
        "email": [],
        "crypto_address": []
      },
      "risk_features": {
        "regulatory": [],
        "technical": [],
        "financial": [],
        "operational": []
      },
      "risk_score": 0.0,
      "source": "Banyan Network.txt"
    }
  },
  {
    "text": "[Section 33] big data values currently issue isolated data islands solved data security control stringent double concern reflects topic long troubling industry xe2 x80 x93 xe2 x80 x9cdata trust system xe2 x80 x9d established difficult build features credibility traceability tamper resistance value sharing blockchain technology speeding applications fields constructing data value network based blockchain pry open trillion dollar big data market perspective solvers industry bottlenecks data openness connectivity value flow require legal institutional policy protection strong solution important reliable carrier scenarios big data applications increasing focus transparency security blockchain technology allows multiple nodes jointly participate data computation recording cross check validity making data 7 x0cbanyan network trustworthy valuable continuous growth sequentially ordered blocks chained data structure reshape ecology data industry future cornerstone era data economy realization value data",
    "metadata": {
      "chunk_id": "97f135269f5f1e4f235db3e0e68e8a47",
      "entities": {
        "email": [],
        "crypto_address": []
      },
      "risk_features": {
        "regulatory": [],
        "technical": [],
        "financial": [],
        "operational": []
      },
      "risk_score": 0.0,
      "source": "Banyan Network.txt"
    }
  },
  {
    "text": "[Section 34] 7 x0cbanyan network trustworthy valuable continuous growth sequentially ordered blocks chained data structure reshape ecology data industry future cornerstone era data economy realization value data integration blockchains help transmit transfer data values establish foundation trusted data connections future participants data industry connected network smart contracts smart assets formed contractual relationships blockchain almighty ledger data value chains based foundation access right confirmation data commercialization data resources depend supporting technology fitting development model sharing economy data value network based blockchain solve problems completely core strengths dvn s decentralization avoid illegitimate data copy interception storage modification possibility theft weakening data value greatly reducing cost trust dvn data sources advantage breakthrough geographical time constraints maximizing degree transparency extendibility efficiency 8 x0cbanyan network",
    "metadata": {
      "chunk_id": "956f97746858891e2ebacf8add8d1252",
      "entities": {
        "email": [],
        "crypto_address": []
      },
      "risk_features": {
        "regulatory": [],
        "technical": [],
        "financial": [],
        "operational": []
      },
      "risk_score": 0.0,
      "source": "Banyan Network.txt"
    }
  },
  {
    "text": "[Section 35] weakening data value greatly reducing cost trust dvn data sources advantage breakthrough geographical time constraints maximizing degree transparency extendibility efficiency 8 x0cbanyan network participants leading greater data liquidity higher data values artificial intelligence industry based dvn data reborn dvn serve data provision infrastructure artificial intelligence supplying data sources data service procurement high performance distributed data processing capabilities meet needs application development ai providing adequate fuels future artificial intelligence 4 business structure large gap commercial data supply data requirements data generally lack liquidity integration extent isolated illiquid uncleansed unprocessed values fully realized dvn provides integrated value network framework participants data industry offering systematic solution connecting data requirements data provision dvn supports value added products service development stages data value cycle providing",
    "metadata": {
      "chunk_id": "789d8956f460da9b93cf6a681506a7e2",
      "entities": {
        "email": [],
        "crypto_address": []
      },
      "risk_features": {
        "regulatory": [],
        "technical": [],
        "financial": [],
        "operational": []
      },
      "risk_score": 0.0,
      "source": "Banyan Network.txt"
    }
  },
  {
    "text": "[Section 36] framework participants data industry offering systematic solution connecting data requirements data provision dvn supports value added products service development stages data value cycle providing fundamental customized support party aggressively actively participate construction optimization 9 x0cbanyan network dvn efficiently promote value gain engine rising double helix dvn data value network double helix structure data stream value stream data stream promotes data aggregation connection access coupling xe2 x80 x9cvalue stream xe2 x80 x9d value stream promotes value mining assessment recording distribution cross section forms closed loop structure connecting data demand data supply slice forms exponential expansion structure promotes value production value acceleration eventually forming engine drives big bang data value data contribution value feedback participants dvn 4 1 link constructing value network data value network dvn created meet needs participants data industry co",
    "metadata": {
      "chunk_id": "34e8ed11c43c55bde091c317b682caea",
      "entities": {
        "email": [],
        "crypto_address": []
      },
      "risk_features": {
        "regulatory": [],
        "technical": [],
        "financial": [],
        "operational": []
      },
      "risk_score": 0.0,
      "source": "Banyan Network.txt"
    }
  },
  {
    "text": "[Section 37] forming engine drives big bang data value data contribution value feedback participants dvn 4 1 link constructing value network data value network dvn created meet needs participants data industry co building values business flow break traditional distance data sources industry applications applying links distributing nodes connect integrate traditional data collection cleansing integration figure lines data fusion value chain dvc formed multiple dvcs overlapping constitute borderless data value network dvn densely populated lines 10 x0cbanyan network dvn parties incorporated unified data value ecology interests participants ensured blockchain technology supporting mechanisms dvn parties grouped unified data security system employing security multi party computation smc framework protocol security zero knowledge ensure security compliance data records processes 4 1 1 dvn collection dvn supports quick easy access multivariate data order address access problems arising differences",
    "metadata": {
      "chunk_id": "d6e41bd2c33ad750339469cec00d36a6",
      "entities": {
        "email": [],
        "crypto_address": []
      },
      "risk_features": {
        "regulatory": [],
        "technical": [],
        "financial": [],
        "operational": []
      },
      "risk_score": 0.0,
      "source": "Banyan Network.txt"
    }
  },
  {
    "text": "[Section 41] taglib dvn standard tagging system equipped data tag access matching association mechanisms etc provides cross source multi dimensional combination joint tag usage services based data integration 4 2 4banyanmaket dvn open application market equipped data supply recommendation demand publishing value matching intermediate custody etc provide open application market based data integration 4 2 5 banyan security suite dvn distributed security package equipped data governance process management risk assessment certification marks etc provide services data security control participants 14 x0cbanyan network 5 technology foundation dvn supports lifecycle management data applications depth combination big data technology blockchain technology data entire data lifecycle interacts dvn dvn api dvn api receives data request rewards payments etc written blockchain records smart contracts sample technology architecture technologies involved sample technology architecture follows crawlers api ftp",
    "metadata": {
      "chunk_id": "915fc718856f0ae0d8ab90aa8d0f23eb",
      "entities": {
        "email": [],
        "crypto_address": []
      },
      "risk_features": {
        "regulatory": [],
        "technical": [],
        "financial": [],
        "operational": []
      },
      "risk_score": 0.0,
      "source": "Banyan Network.txt"
    }
  },
  {
    "text": "[Section 42] api receives data request rewards payments etc written blockchain records smart contracts sample technology architecture technologies involved sample technology architecture follows crawlers api ftp xdbc streaming protocols multidata interactions 15 x0cbanyan network distributed file systems hdfs distributed databases hbase tool sets hash algorithm data clean box etc data mining algorithms decision trees random forests logical regression clustering machine learning etc big data platforms tools apache kylin presto impala sparks etc 6 theoretical framework 6 1 laws data value embedded parameters value data reflected application circulation practical uses value data realized validation mature business models laws data value summarized xef xbc x9a law data silence accelerates devaluation second law data circulation produces values law integrated data promotes value added laws denote data value v timeliness related age data data liquidity dy data integrability f 6 2 parameter data quality",
    "metadata": {
      "chunk_id": "41d354479da7622b3b27a54338ad2bca",
      "entities": {
        "email": [],
        "crypto_address": []
      },
      "risk_features": {
        "regulatory": [],
        "technical": [],
        "financial": [],
        "operational": []
      },
      "risk_score": 0.0,
      "source": "Banyan Network.txt"
    }
  },
  {
    "text": "[Section 43] law data circulation produces values law integrated data promotes value added laws denote data value v timeliness related age data data liquidity dy data integrability f 6 2 parameter data quality data quality q developed considering current international standards iso8000 relevant parameters national industry 16 x0cbanyan network standards reflecting order consistency accuracy integrity data 6 3 parameter data quality data liquidity dy related frequency data processed traded circulated applied processing trading circulation change data value v quality q frequency application fq categorized according industry experience number level data uses expressed following function xef xbc x9a dy f1 xce x94v xce x94q fq 6 4 data liquidity integrability data integrability f related degree interconnectivity association different data sources f value equal dimension actual association data chain 6 5 data timeliness data age reflects data timeliness related time t data generation time t xce x94q",
    "metadata": {
      "chunk_id": "58d345641f5b4a94937d1ec7def9634d",
      "entities": {
        "email": [],
        "crypto_address": []
      },
      "risk_features": {
        "regulatory": [],
        "technical": [],
        "financial": [],
        "operational": []
      },
      "risk_score": 0.0,
      "source": "Banyan Network.txt"
    }
  },
  {
    "text": "[Section 44] association different data sources f value equal dimension actual association data chain 6 5 data timeliness data age reflects data timeliness related time t data generation time t xce x94q data cleansing organizing lead changes data quality time t xce x94dy data processing trading circulation lead changes data liquidity time t xce x94f data integration occurs specific function follows f2 t xef xbc x8ct xce x94q xef xbc x8ct xce x94dy xef xbc x8ct xce x94f 17 x0cbanyan network longer data generation time t worse data timeliness older data age longer times t xce x94q t xce x94dy t xce x94f worse data timeliness 6 6 data value function according definition data value v expressed following function v f3 q xef xbc x8cdy xef xbc x8cf xef xbc x8ca v proportional q dy f inversely proportional 6 7 decision mechanisms definition data parameter functions definitions values data quality parameters q xe3 x80 x81f1 xe3 x80 x81f2 xe3 x80 x81f3 xe3 x80 x81f4 7 5 xe3 x80 x81f5 7 5 depend consensus",
    "metadata": {
      "chunk_id": "bf9a411f0adaf9b38643234cce886801",
      "entities": {
        "email": [],
        "crypto_address": []
      },
      "risk_features": {
        "regulatory": [],
        "technical": [],
        "financial": [],
        "operational": []
      },
      "risk_score": 0.0,
      "source": "Banyan Network.txt"
    }
  },
  {
    "text": "[Section 45] 6 7 decision mechanisms definition data parameter functions definitions values data quality parameters q xe3 x80 x81f1 xe3 x80 x81f2 xe3 x80 x81f3 xe3 x80 x81f4 7 5 xe3 x80 x81f5 7 5 depend consensus token holders 7 6 7 rules tokens 7 1 introduction tokens dvn token bbn token provides support banyanchain usage scenarios include data access bonuses data cleansing rewards data usage payments etc 18 x0cbanyan network 7 2 token details purpose bbn issuance encourage developers users ecosystems enhance quality degree integration data availability entire network fundamentally promoting regulation positive development data industry providing solid support protection final data applications dvn practical problems solved blockchain features e g traceability tamper resistance data cleansing integration product delivery lot strong cases bbn consumption needed example participants use bbns stages data governance commercialization participate registration rewards paid bbns completion data",
    "metadata": {
      "chunk_id": "2f47a9f4770aea919f3168269b87f479",
      "entities": {
        "email": [],
        "crypto_address": []
      },
      "risk_features": {
        "regulatory": [],
        "technical": [],
        "financial": [],
        "operational": []
      },
      "risk_score": 0.0,
      "source": "Banyan Network.txt"
    }
  },
  {
    "text": "[Section 46] integration product delivery lot strong cases bbn consumption needed example participants use bbns stages data governance commercialization participate registration rewards paid bbns completion data governance product processing prosperity data industry support value bbn 7 3 circulation model banyanchain design complete set bbn circulation mechanism rich bbn usage scenarios ensuring bbn liquidity series intelligent contracts introducing rewards contract irc responsible calculating confirming reward introduction data data sources data banyanchain form data products services 19 x0cbanyan network certain reward distributed data source accordance proportion defined governance committee computing rewards contract crc responsible calculating confirming reward participants data governance payment certain deposit deposit required application data governance obtain certain number rights data processing optimization processing tools provided banyanchain nodes provide computing resources data",
    "metadata": {
      "chunk_id": "ce8e582c09f0e0a69dc5cb4fc05ffe01",
      "entities": {
        "email": [],
        "crypto_address": []
      },
      "risk_features": {
        "regulatory": [
          "fine"
        ],
        "technical": [],
        "financial": [],
        "operational": []
      },
      "risk_score": 12.0,
      "source": "Banyan Network.txt"
    }
  },
  {
    "text": "[Section 47] certain deposit deposit required application data governance obtain certain number rights data processing optimization processing tools provided banyanchain nodes provide computing resources data certain reward distributed data governor according ratio established governance committee specific function follows deposit f4 v0 v0 data value v deposit reward f5 xce x94v xef xbc x8ctime xce x94v increase data value processing data governor unable finish data governance promised time deposit confiscated prevent data source occupied long time governance apply pay contract apc responsible calculation confirmation payment data users data service specific payment shall implemented accordance standards established governance committee 20 x0cbanyan network transaction contract tc responsible calculating confirming cost data governance fees use products addition richer richer usage environments data governance positions scenarios rule possibility adding contracts process system operation 7 4",
    "metadata": {
      "chunk_id": "533ae89cd87f0dc14256470a8c47aed9",
      "entities": {
        "email": [],
        "crypto_address": []
      },
      "risk_features": {
        "regulatory": [],
        "technical": [],
        "financial": [],
        "operational": []
      },
      "risk_score": 0.0,
      "source": "Banyan Network.txt"
    }
  },
  {
    "text": "[Section 48] confirming cost data governance fees use products addition richer richer usage environments data governance positions scenarios rule possibility adding contracts process system operation 7 4 holding weighted voting rights holds bbn obtain voting rights getting mortgage token voting rights positively correlated number mortgages mortgage time governance governance committee includes limited introduction termination data sources data valuation data governance rewards payment schemes data usage etc adjustments decided group voting governance system 8 governance mechanism 8 1 underlying operation underlying blockchain dvn based ethereum operated public mature platform supports smart contracts community active foundation works 21 x0cbanyan network rule use antshares hpb independently developed technologies future 8 2 smart contracts aim develop generic smart contract templates business models processes strong commonalities network uniformly vast majority business scenarios dvn plan develop",
    "metadata": {
      "chunk_id": "1295ece5f28e11d89d31e8ecb25f7de2",
      "entities": {
        "email": [],
        "crypto_address": []
      },
      "risk_features": {
        "regulatory": [],
        "technical": [],
        "financial": [],
        "operational": []
      },
      "risk_score": 0.0,
      "source": "Banyan Network.txt"
    }
  },
  {
    "text": "[Section 49] technologies future 8 2 smart contracts aim develop generic smart contract templates business models processes strong commonalities network uniformly vast majority business scenarios dvn plan develop smart contract repository special tags specific categories subsequent additions distribute announcements expand dynamically efficiently operate flexible configurations 8 3 consensus mechanism data dvn introduction governance processing use associated reward payment token circulation dpos consensus mechanism recording writing 8 4 tripartite model adopt tripartite model network co governance including dvn decentralized governance committee participant ensure operation entire value system operation mechanism reasonable appropriate limited distribution rights governance committee responsible rule developing participant responsible rule execution dvn charge 22 x0cbanyan network rule operation shown figure 9 technology applications 9 1 blockchain applications current mainstream digital tokens",
    "metadata": {
      "chunk_id": "62ffaafa5b9d539a3413b2ea55ad6c10",
      "entities": {
        "email": [],
        "crypto_address": []
      },
      "risk_features": {
        "regulatory": [],
        "technical": [],
        "financial": [],
        "operational": []
      },
      "risk_score": 0.0,
      "source": "Banyan Network.txt"
    }
  },
  {
    "text": "[Section 50] developing participant responsible rule execution dvn charge 22 x0cbanyan network rule operation shown figure 9 technology applications 9 1 blockchain applications current mainstream digital tokens including bitcoin ether based blockchain core technology ensure verification currency transaction records tamper resistance de centralization block validation storage dvn token bbn uses blockchain technological support circulation addition ensuring security trustworthiness convenience token circulation transaction allows bbn users establish confidence market demand giving bbn opportunity circulate large volumes preserve value appreciate like major digital tokens bitcoin ether 23 x0cbanyan network 9 2 applications artificial intelligence artificial intelligence based mainstream method deep learning hot area high value added applications big data useful tool big data collection cleansing integration dvn hand use mature data material foundation training artificial intelligence develop ai",
    "metadata": {
      "chunk_id": "9fe42893c2c459c59444ad2e6ca97698",
      "entities": {
        "crypto_project": [
          "token bbn"
        ],
        "email": [],
        "crypto_address": []
      },
      "risk_features": {
        "regulatory": [],
        "technical": [],
        "financial": [],
        "operational": []
      },
      "risk_score": 0.0,
      "source": "Banyan Network.txt"
    }
  },
  {
    "text": "[Section 51] learning hot area high value added applications big data useful tool big data collection cleansing integration dvn hand use mature data material foundation training artificial intelligence develop ai applications fields market products hand uses ai simulate manual data collection cleansing integration processes performed data engineers aim develop automated tools packages implement tasks described improving process efficiency significantly reducing leakage security risks human negligence arising human factors data processing 10 acknowledgements design development bbn network rely core team s deep understanding insight data industry support trust key customers partners industry organizations contributions engineering experts industry veterans fields blockchain artificial intelligence like express sincere gratitude past contributors participated technology business management dvn resource contributors participating model platform funds etc bbn issuance look forward working participants",
    "metadata": {
      "chunk_id": "33da2ac21526580d24694ae5a4e827eb",
      "entities": {
        "email": [],
        "crypto_address": []
      },
      "risk_features": {
        "regulatory": [],
        "technical": [],
        "financial": [],
        "operational": []
      },
      "risk_score": 0.0,
      "source": "Banyan Network.txt"
    }
  },
  {
    "text": "[Section 52] express sincere gratitude past contributors participated technology business management dvn resource contributors participating model platform funds etc bbn issuance look forward working participants interested endeavor build limitless future data integration 24 x0cbanyan network banyannetwork team official website http www banyanbbt org twitter https www twitter com banyan network telegram chat https t bbnglobalfans reddit https www reddit com r banyannetwork announcements https t bbnannouncements official medium https medium com banyannetwork 25 x0cbanyan network references 1 m serrato xef xbc x8c j ramirezthe strategic business value big data springer international publishing 2017 2 l furtado xef xbc x8c m dutra xef xbc x8c d macedo value creation big data scenarios literature survey journal industrial integration management 2017 1750002 3 satoshi nakamoto bitcoin xef xbc x9aa peer peer electronic cash system white paper october 31 2008 4 antonopoulos andreas bitcoin security model",
    "metadata": {
      "chunk_id": "ee1fb425cdd9548f150e0a17959b816e",
      "entities": {
        "email": [],
        "crypto_address": []
      },
      "risk_features": {
        "regulatory": [],
        "technical": [],
        "financial": [],
        "operational": []
      },
      "risk_score": 0.0,
      "source": "Banyan Network.txt"
    }
  },
  {
    "text": "[Section 53] industrial integration management 2017 1750002 3 satoshi nakamoto bitcoin xef xbc x9aa peer peer electronic cash system white paper october 31 2008 4 antonopoulos andreas bitcoin security model trust computation radar o reilly retrieved 19 november 2016 5 lakhani karim r truth blockchain harvard business review harvard university retrieved 2017 01 17 6 thompson jeffrey rise bitcoins altcoins xe2 x80 x94future digital currency epoch times retrieved 2013 12 29 7 j s xc3 xa4nger xef xbc x8cc richthammer s hassan g pernul trust big data roadmap research workshop security highly connected systems 2014 278 282 8 popper nathaniel business giants announce creation computing system based ethereum xe2 x80 x93 nytimes com 9 ethereum url https en m wikipedia org wiki ethereum 10 proof stake url https en m wikipedia org wiki proof stake 11 delegated proof stake dpos url https bitshares org technology delegated proof ofstake consensus 12 de o leary artificial intelligence big data ieee intelligent",
    "metadata": {
      "chunk_id": "561b6627a085f173df2ee2b2ca669aea",
      "entities": {
        "email": [],
        "crypto_address": []
      },
      "risk_features": {
        "regulatory": [],
        "technical": [],
        "financial": [],
        "operational": []
      },
      "risk_score": 0.0,
      "source": "Banyan Network.txt"
    }
  }
]